achilles/__init__.py
achilles/archive/__init__.py
achilles/archive/Protocol/__init__.py
achilles/archive/Protocol/cortex.py
achilles/archive/Protocol/cortex_function.py
achilles/archive/Protocol/cortex_node.py
achilles/archive/Protocol/cortex_node2.py
achilles/archive/Protocol/cortex_node3.py
achilles/archive/Protocol/cortex_node4.py
achilles/archive/Protocol/cortex_server.py
achilles/lineReceiver/__init__.py
achilles/lineReceiver/achilles_args.txt
achilles/lineReceiver/achilles_config.yaml
achilles/lineReceiver/achilles_controller.py
achilles/lineReceiver/achilles_function.py
achilles/lineReceiver/achilles_main.py
achilles/lineReceiver/achilles_node.py
achilles/lineReceiver/achilles_node2.py
achilles/lineReceiver/achilles_node3.py
achilles/lineReceiver/achilles_node4.py
achilles/lineReceiver/achilles_server.py
achilles/lineReceiver/Cythonized/__init__.py
achilles/lineReceiver/Cythonized/achilles_function.py
achilles/lineReceiver/Cythonized/compile.py
achilles-0.0.196.dist-info/LICENSE
achilles-0.0.196.dist-info/METADATA
achilles-0.0.196.dist-info/WHEEL
achilles-0.0.196.dist-info/top_level.txt
achilles-0.0.196.dist-info/RECORD
