Metadata-Version: 2.1
Name: achilles
Version: 0.0.196
Summary: Distributed/parallel computing in modern Python based on the multiprocessing.Pool API (map, imap, imap_unordered).
Home-page: https://github.com/adpena/achilles
Author: Alejandro Peña
Author-email: adpena@gmail.com
License: UNKNOWN
Platform: UNKNOWN
Classifier: Programming Language :: Python :: 3
Classifier: License :: OSI Approved :: MIT License
Classifier: Operating System :: OS Independent
Requires-Dist: dill
Requires-Dist: python-dotenv
Requires-Dist: twisted
Requires-Dist: pyyaml
Requires-Dist: multiprocess
